{
    "prepare_queue": {
        "installed": [],
        "uninstalled": []
    },
    "config_munge": {
        "files": {}
    },
    "installed_plugins": {
        "cordova-plugin-datepicker": {
            "PACKAGE_NAME": "com.rantcar.hancoma"
        },
        "cordova-plugin-sim": {
            "PACKAGE_NAME": "com.rantcar.hancoma"
        }
    },
    "dependent_plugins": {},
    "modules": [
        {
            "file": "plugins/cordova-plugin-sim/www/sim.js",
            "id": "cordova-plugin-sim.Sim",
            "pluginId": "cordova-plugin-sim",
            "merges": [
                "window.plugins.sim"
            ]
        }
    ],
    "plugin_metadata": {
        "cordova-plugin-datepicker": "0.9.3",
        "cordova-plugin-sim": "1.3.2"
    }
}